Workbook

Sheet Investment summary
A1: BATA INDIA LTD - EQUITY RESEARCH NOTE
A3: Recommendation | B3: SELL
A4: CMP (Rs) | B4: 608
A5: Fair Value (Rs) | B5: 314
A6: Upside / Downside | B6: -0.48
A9: SCENARIO ANALYSIS
A11: Bull Case (10% WACC, 7% TGR) | B11: Rs 681 (+8%)
A12: Base Case (11% WACC, 5% TGR) | B12: Rs 314 (-48%)
A13: Bear Case (13% WACC, 4% TGR) | B13: Rs 182 (-71%)
A15: PEER VALUATION COMPARISON
A17: Company | B17: CMP | C17: P/E | D17: EV/EBITDA
A18: Bata India | B18: 608 | C18: 40.7x | D18: 18x
A19: Metro Brands | B19: 896 | C19: 62.7x | D19: 28x
A20: Relaxo | B20: 238 | C20: 35.3x | D20: 22x
A21: Bata trades at 40.7x P/E. Metro Brands at 62.7x justifies premium due to stronger ROCE (19.4% vs Bata's 15.1%) and faster growth. Bata's multiple looks stretched given stalling revenue.
A23: At 40x P/E Bata trades closer to premium peers despite lower ROCE and slower growth. Market appears to be pricing a successful turnaround. Our model suggests this optimism is overestimated.
A26: KEY DRIVERS
A27: 1. Revenue growth from store expansion (5-6%) and SSSG (3-4%) gives 8-10% blended growth
A28: 2. EBITDA margins stable at 22-23% with no major cost changes expected
A29: 3. Capex slightly above depreciation as Bata continues adding stores
A30: 4. At 40.7x P/E market is pricing sustained double digit growth. But growth is store expansion driven not productivity driven. This mismatch between perceived and actual growth quality is the core reason for our SELL call.
A34: KEY RISKS
A35: 1. Growth relies on new stores not existing store productivity
A36: 2. Borrowings have risen from 1032 to 1446 crore over 5 years
A37: 3. Flat SSSG points to weak brand pull in current market
A38: 4. Market may be pricing a turnaround. If Bata executes on premiumization and D2C expansion the SELL thesis breaks down.
... A43: 2. Downside is asymmetric. Bull case upside is only 12 percent vs base case downside of 48 percent and bear case of 71 percent. Risk reward strongly favors the bear case.

Sheet P&L
A1: Bata India Ltd - Profit & Loss (₹ Crores) | B1: FY21 | C1: FY22 | D1: FY23 | E1: FY24 | F1: FY25 | G1: FY26 | H1: FY27 | I1: FY28 | J1: FY29 | K1: FY30
A2: Revenue (Sales) | B2: 1708 | C2: 2388 | D2: 3452 | E2: 3479 | F2: 3489 | G2: =F2*(1+Assumptions!B2) -> 3773.3535 | H2: =G2*(1+Assumptions!C2) -> 4159.7449 | I2: =H2*(1+Assumptions!D2) -> 4585.7028 | J2: =I2*(1+Assumptions!E2) -> 5006.6703 | K2: =J2*(1+Assumptions!F2) -> 5414.7139
A3: Expenses | B3: 1540 | C3: 1960 | D3: 2647 | E3: 2682 | F3: 2736 | G3: =G2-G4 -> 2943.2157 | H3: =H2-H4 -> 3244.601 | I3: =I2-I4 -> 3576.8482 | J3: =J2-J4 -> 3855.1361 | K3: =K2-K4 -> 4169.3297
A4: EBITDA | B4: =B2-B3 -> 168 | C4: =C2-C3 -> 428 | D4: =D2-D3 -> 805 | E4: =E2-E3 -> 797 | F4: =F2-F3 -> 753 | G4: =G2*Assumptions!B3 -> 830.13777 | H4: =H2*Assumptions!C3 -> 915.14388 | I4: =I2*Assumptions!D3 -> 1008.8546 | J4: =J2*Assumptions!E3 -> 1151.5342 | K4: =K2*Assumptions!F3 -> 1245.3842
A5: EBITDA Margin % | B5: =B4/B2 -> 0.098360656 | C5: =C4/C2 -> 0.17922948 | D5: =D4/D2 -> 0.23319815 | E5: =E4/E2 -> 0.22908882 | F5: =F4/F2 -> 0.21582115 | G5: =G4/G2 -> 0.22 | H5: =H4/H2 -> 0.22 | I5: =I4/I2 -> 0.22 | ... K5: =K4/K2 -> 0.23
A7: Depreciation | B7: 265 | C7: 242 | D7: 295 | E7: 339 | F7: 371 | G7: =G2*Assumptions!B4 -> 415.06889 | H7: =H2*Assumptions!C4 -> 457.57194 | I7: =I2*Assumptions!D4 -> 504.42731 | J7: =J2*Assumptions!E4 -> 550.73373 | K7: =K2*Assumptions!F4 -> 595.61853
A8: EBIT | B8: =B4-B7 -> -97 | C8: =C4-C7 -> 186 | D8: =D4-D7 -> 510 | E8: =E4-E7 -> 458 | F8: =F4-F7 -> 382 | G8: =G4-G7 -> 415.06889 | H8: =H4-H7 -> 457.57194 | I8: =I4-I7 -> 504.42731 | ... K8: =K4-K7 -> 649.76567
A10: Other Income | B10: 87 | C10: 54 | D10: 39 | E10: 19 | F10: 186 | G10: 50 | H10: 50 | I10: 50 | J10: 50 | K10: 50
A11: Interest | B11: 108 | C11: 99 | D11: 118 | E11: 126 | F11: 141 | G11: =Assumptions!B6 -> 150 | H11: =Assumptions!C6 -> 150 | I11: =Assumptions!D6 -> 150 | J11: =Assumptions!E6 -> 155 | K11: =Assumptions!F6 -> 155
A12: Profit Before Tax (PBT) | B12: =B8+B10-B11 -> -118 | C12: =(C8+C10)-C11 -> 141 | D12: =D8+D10-D11 -> 431 | E12: =E8+E10-E11 -> 351 | F12: =F8+F10-F11 -> 427 | G12: =G8+G10-G11 -> 315.06889 | H12: =H8+H10-H11 -> 357.57194 | I12: =I8+I10-I11 -> 404.42731 | J12: =J8+J10-J11 -> 495.80043 | K12: =K8+K10-K11 -> 544.76567
A13: Tax | B13: =B12-B14 -> -29 | C13: =C12-C14 -> 38 | D13: =D12-D14 -> 108 | E13: =E12-E14 -> 88 | F13: =F12-F14 -> 96 | G13: =G12*Assumptions!B5 -> 78.767221 | H13: =H12*Assumptions!C5 -> 89.392985 | I13: =I12*Assumptions!D5 -> 101.10683 | J13: =J12*Assumptions!E5 -> 123.95011 | K13: =K12*Assumptions!F5 -> 136.19142
A14: Net Profit (PAT) | B14: -89 | C14: 103 | D14: 323 | E14: 263 | F14: 331 | G14: =G12-G13 -> 236.30166 | H14: =H12-H13 -> 268.17895 | I14: =I12-I13 -> 303.32048 | J14: =J12-J13 -> 371.85033 | K14: =K12-K13 -> 408.57425
A15: PAT Margin % | B15: =B14/B2 -> -0.052107728 | C15: =C14/C2 -> 0.043132328 | D15: =D14/D2 -> 0.093568946 | E15: =E14/E2 -> 0.075596436 | F15: =F14/F2 -> 0.09486959 | G15: =G14/G2 -> 0.062623781 | H15: =H14/H2 -> 0.064470048 | I15: =I14/I2 -> 0.066144819 | ... K15: =K14/K2 -> 0.075456295
A16: EPS | B16: -6.95 | C16: 8.01 | D16: 25.13 | E16: 20.42 | F16: 25.73

Sheet Balance Sheet
A1: Bata India Ltd - Balance Sheet (₹ Crores) | B1: FY21 | C1: FY22 | D1: FY23 | E1: FY24 | F1: FY25
A2: Equity Capital | B2: 64 | C2: 64 | D2: 64 | E2: 64 | F2: 64
A3: Reserves | B3: 1694 | C3: 1750 | D3: 1374 | E3: 1463 | F3: 1511
A4: Total Equity | B4: =B2+B3 -> 1758 | C4: =C2+C3 -> 1814 | D4: =D2+D3 -> 1438 | E4: =E2+E3 -> 1527 | F4: =F2+F3 -> 1575
A5: Borrowings | B5: 1032 | C5: 1094 | D5: 1246 | E5: 1357 | F5: 1446
A6: Other Liabilities | B6: 542 | C6: 616 | D6: 587 | E6: 466 | F6: 801
A7: Total Liabilities | B7: =SUM(B4:B6) -> 3332 | C7: =SUM(C4:C6) -> 3524 | D7: =SUM(D4:D6) -> 3271 | E7: =SUM(E4:E6) -> 3350 | F7: =SUM(F4:F6) -> 3822
A9: Fixed Assets | B9: 1120 | C9: 1226 | D9: 1392 | E9: 1509 | F9: 1800
A10: CWIP | B10: 34 | C10: 5 | D10: 4 | E10: 4 | F10: 14
A11: Investments | B11: 0 | C11: 0 | D11: 0 | E11: 0 | F11: 1
A12: Other Assets | B12: 2179 | C12: 2294 | D12: 1876 | E12: 1837 | F12: 2008
A13: Total Assets | B13: =SUM(B9:B12) -> 3333 | C13: =SUM(C9:C12) -> 3525 | D13: =SUM(D9:D12) -> 3272 | E13: =SUM(E9:E12) -> 3350 | F13: =SUM(F9:F12) -> 3823

Sheet Cash flow
A1: Bata India Ltd - Cash Flow Statement (₹ Crores) | B1: FY21 | C1: FY22 | D1: FY23 | E1: FY24 | F1: FY25
A2: Cash from Operations | B2: 461 | C2: 212 | D2: 629 | E2: 453 | F2: 738
A3: Cash from Investing | B3: -53 | C3: 93 | D3: 439 | E3: 40 | F3: 53
A4: Cash from Financing | B4: -369 | C4: -341 | D4: -1011 | E4: -518 | F4: -638
A5: Net Cash Flow | B5: =SUM(B2:B4) -> 39 | C5: =SUM(C2:C4) -> -36 | D5: =SUM(D2:D4) -> 57 | E5: =SUM(E2:E4) -> -25 | F5: =SUM(F2:F4) -> 153

Sheet Assumptions
A1: ASSUMPTIONS | B1: FY26 | C1: FY27 | D1: FY28 | E1: FY29 | F1: FY30
A2: Revenue Growth % | B2: =(1+B7)*(1+B8)-1 -> 0.0815 | C2: =(1+C7)*(1+C8)-1 -> 0.1024 | D2: =(1+D7)*(1+D8)-1 -> 0.1024 | E2: =(1+E7)*(1+E8)-1 -> 0.0918 | F2: =(1+F7)*(1+F8)-1 -> 0.0815
A3: EBITDA Margin % | B3: 0.22 | C3: 0.22 | D3: 0.22 | E3: 0.23 | F3: 0.23
A4: Depreciation (% of Revenue) | B4: 0.11 | C4: 0.11 | D4: 0.11 | E4: 0.11 | F4: 0.11
A5: Tax Rate | B5: 0.25 | C5: 0.25 | D5: 0.25 | E5: 0.25 | F5: 0.25
A6: Interest Cost (fixed ₹ Cr) | B6: 150 | C6: 150 | D6: 150 | E6: 155 | F6: 155
A7: Store Count Growth % | B7: 0.05 | C7: 0.06 | D7: 0.06 | E7: 0.06 | F7: 0.05
A8: SSSG | B8: 0.03 | C8: 0.04 | D8: 0.04 | E8: 0.03 | F8: 0.03
A10: Assumption | B10: Reasoning
A11: Revenue Growth % | B11: Revenue growth derived as (1 + Store Growth) × (1 + SSSG) - 1, not assumed directly. FY26: 5% stores × 3% SSSG = 8.15%.
A14: EBITDA Margin % | B14: Margin has been stable at 22-23% for 3 consecutive years. No major cost tailwinds or headwinds expected. Holding flat is the most defensible assumption.
A17: Depreciation (% of Revenue) | B17: FY25 depreciation was 371 on revenue 3489 = 10.6%. Bata continues store refurbishments and capex. Slight uptick to 11% accounts for new store additions.
A20: Tax Rate | B20: Consistent at 25% for FY23, FY24, FY25. No reason to deviate.
A22: Interest Cost (fixed ₹ Cr) | B22: Borrowings have risen every year (1032 to 1446 over 5 years). Interest rising accordingly. 150 is a slight step up from FY25's 141.
A25: FY29-30 Revenue Growth | B25: Growth moderating as Bata reaches scale. Tier-2 expansion continues but SSSG plateaus. Step down to 9% in FY30 reflects mature retail cycle.
A28: FY29-30 EBITDA Margin 23% | B28: Slight improvement from 22% as operating leverage kicks in on higher revenue base. Fixed costs spread over larger topline.

Sheet DCF
A1: Bata India Ltd - DCF Valuation (₹ Crores) | B1: FY26 | C1: FY27 | D1: FY28 | E1: FY29 | F1: FY30
A2: Free Cash Flow Calculation | H2: WACC: | I2: 11% - blended cost of capital for mid-cap Indian consumer
A3: EBIT | B3: ='P&L'!G8 -> 415.06889 | C3: ='P&L'!H8 -> 457.57194 | D3: ='P&L'!I8 -> 504.42731 | E3: ='P&L'!J8 -> 600.80043 | F3: ='P&L'!K8 -> 649.76567 | H3: Terminal Growth Rate: | I3: 5% - conservative, below India nominal GDP growth
A4: Tax on EBIT | B4: =B3*0.25 -> 103.76722 | C4: =C3*0.25 -> 114.39298 | D4: =D3*0.25 -> 126.10683 | E4: =E3*0.25 -> 150.20011 | F4: =F3*0.25 -> 162.44142 | H4: Capex: | I4: 115% of Depreciation - store expansion means asset base growing, capex slightly ahead of depreciation. Consistent with Bata's store addition strategy.
A5: NOPAT | B5: =B3-B4 -> 311.30166 | C5: =C3-C4 -> 343.17895 | D5: =D3-D4 -> 378.32048 | E5: =E3-E4 -> 450.60033 | F5: =F3-F4 -> 487.32425
A6: Add: Depreciation | B6: ='P&L'!G7 -> 415.06889 | C6: ='P&L'!H7 -> 457.57194 | D6: ='P&L'!I7 -> 504.42731 | E6: ='P&L'!J7 -> 550.73373 | F6: ='P&L'!K7 -> 595.61853
A7: Less: Capex | B7: =B6*1.15 -> 477.32922 | C7: =C6*1.15 -> 526.20773 | D7: =D6*1.15 -> 580.0914 | E7: =E6*1.15 -> 633.34379 | F7: =F6*1.15 -> 684.96131 | H7: Net Debt: | I7: 1246 crore - Borrowings minus estimated cash
A8: Free Cash Flow (FCF) | B8: =B5+B6-B7 -> 249.04133 | C8: =C5+C6-C7 -> 274.54316 | D8: =D5+D6-D7 -> 302.65638 | E8: =E5+E6-E7 -> 367.99027 | F8: =F5+F6-F7 -> 397.98147 | H8: Shares Outstanding: | I8: 12.85 crore - derived from Market Cap / CMP
A10: DCF Inputs
A11: WACC | B11: 0.11 | C11: 0.11 | D11: 0.11 | E11: 0.11 | F11: 0.11
A12: Terminal Growth Rate | B12: 0.05 | C12: 0.05 | D12: 0.05 | E12: 0.05 | F12: 0.05
A13: Terminal Value | B13: =F8*(1+B12)/(B11-B12) -> 6964.6758
A14: PV of Terminal Value | B14: =B13/(1+B11)^5 -> 4133.1961
A15: PV of FCFs | B15: =B8/(1+B11)^1 + C8/(1+B11)^2 + D8/(1+B11)^3 + E8/(1+B11)^4 + F8/(1+B11)^5 -> 1147.0759
A16: Total Enterprise Value | B16: =B14+B15 -> 5280.272
A17: Less: Net Debt | B17: 1246
A18: Equity Value | B18: =B16-B17 -> 4034.272
A19: Shares Outstanding | B19: 12.85
A20: Fair Value Per Share | B20: =B18/B19 -> 313.95113
A23: SENSITIVITY ANALYSIS -Fair Value Per Share
A25: WACC / Terminal Growth Rate | B25: 0.04 | C25: 0.05 | D25: 0.06 | E25: 0.07
A26: 0.1 | B26: =(((F8*(1+4%)/(10%-4%))/(1+10%)^5)+(B8/(1+10%)^1+C8/(1+10%)^2+D8/(1+10%)^3+E8/(1+10%)^4+F8/(1+10%)^5)-1246)/12.85 -> 328.13027 | C26: =(((D8*(1+5%)/(10%-5%))/(1+10%)^3)+(B8/(1+10%)^1+C8/(1+10%)^2+D8/(1+10%)^3)-1246)/12.85 -> 327.61722 | D26: =(((D8*(1+6%)/(10%-6%))/(1+10%)^3)+(B8/(1+10%)^1+C8/(1+10%)^2+D8/(1+10%)^3)-1246)/12.85 -> 424.94377 | E26: =(((F8*(1+7%)/(10%-7%))/(1+10%)^5)+(B8/(1+10%)^1+C8/(1+10%)^2+D8/(1+10%)^3+E8/(1+10%)^4+F8/(1+10%)^5)-1246)/12.85 -> 680.69408
A27: 0.11 | B27: =(((F8*(1+4%)/(11%-4%))/(1+11%)^5)+(B8/(1+11%)^1+C8/(1+11%)^2+D8/(1+11%)^3+E8/(1+11%)^4+F8/(1+11%)^5)-1246)/12.85 -> 265.37549 | C27: =(((F8*(1+5%)/(11%-5%))/(1+11%)^5)+(B8/(1+11%)^1+C8/(1+11%)^2+D8/(1+11%)^3+E8/(1+11%)^4+F8/(1+11%)^5)-1246)/12.85 -> 313.95113 | D27: =(((F8*(1+6%)/(11%-6%))/(1+11%)^5)+(B8/(1+11%)^1+C8/(1+11%)^2+D8/(1+11%)^3+E8/(1+11%)^4+F8/(1+11%)^5)-1246)/12.85 -> 381.95702 | E27: =(((F8*(1+7%)/(11%-7%))/(1+11%)^5)+(B8/(1+11%)^1+C8/(1+11%)^2+D8/(1+11%)^3+E8/(1+11%)^4+F8/(1+11%)^5)-1246)/12.85 -> 483.96586
A28: 0.12 | B28: =(((F8*(1+4%)/(12%-4%))/(1+12%)^5)+(B8/(1+12%)^1+C8/(1+12%)^2+D8/(1+12%)^3+E8/(1+12%)^4+F8/(1+12%)^5)-1246)/12.85 -> 218.37097 | C28: =(((F8*(1+5%)/(12%-5%))/(1+12%)^5)+(B8/(1+12%)^1+C8/(1+12%)^2+D8/(1+12%)^3+E8/(1+12%)^4+F8/(1+12%)^5)-1246)/12.85 -> 253.51889 | D28: =(((F8*(1+6%)/(12%-6%))/(1+12%)^5)+(B8/(1+12%)^1+C8/(1+12%)^2+D8/(1+12%)^3+E8/(1+12%)^4+F8/(1+12%)^5)-1246)/12.85 -> 300.38278 | E28: =(((F8*(1+7%)/(12%-7%))/(1+12%)^5)+(B8/(1+12%)^1+C8/(1+12%)^2+D8/(1+12%)^3+E8/(1+12%)^4+F8/(1+12%)^5)-1246)/12.85 -> 365.99223
A29: 0.13 | B29: =(((F8*(1+4%)/(13%-4%))/(1+13%)^5)+(B8/(1+13%)^1+C8/(1+13%)^2+D8/(1+13%)^3+E8/(1+13%)^4+F8/(1+13%)^5)-1246)/12.85 -> 181.8642 | C29: =(((F8*(1+5%)/(13%-5%))/(1+13%)^5)+(B8/(1+13%)^1+C8/(1+13%)^2+D8/(1+13%)^3+E8/(1+13%)^4+F8/(1+13%)^5)-1246)/12.85 -> 208.24655 | D29: =(((F8*(1+6%)/(13%-6%))/(1+13%)^5)+(B8/(1+13%)^1+C8/(1+13%)^2+D8/(1+13%)^3+E8/(1+13%)^4+F8/(1+13%)^5)-1246)/12.85 -> 242.16671 | E29: =(((F8*(1+7%)/(13%-7%))/(1+13%)^5)+(B8/(1+13%)^1+C8/(1+13%)^2+D8/(1+13%)^3+E8/(1+13%)^4+F8/(1+13%)^5)-1246)/12.85 -> 287.39359
